LICENSE
MANIFEST.in
README.md
env.py
local_env.py
setup.py
env.py.egg-info/PKG-INFO
env.py.egg-info/SOURCES.txt
env.py.egg-info/dependency_links.txt
env.py.egg-info/top_level.txt