Metadata-Version: 1.0
Name: env.py
Version: 0.2.2
Summary: Easily manage your python application settings for different environments
Home-page: https://github.com/abhinavsingh/env.py
Author: Abhinav Singh
Author-email: mailsforabhinav@gmail.com
License: BSD
Platform: UNKNOWN
Classifier: Development Status :: 4 - Beta
Classifier: Environment :: Web Environment
Classifier: Intended Audience :: Developers
Classifier: Intended Audience :: System Administrators
Classifier: License :: OSI Approved :: BSD License
Classifier: Operating System :: MacOS
Classifier: Operating System :: POSIX
Classifier: Operating System :: Unix
Classifier: Operating System :: Microsoft
Classifier: Operating System :: OS Independent
Classifier: Programming Language :: Python :: 2.7
